demo/demo_1_shepp_logan.py
demo/demo_2_large_object.py
demo/demo_3_cropped_center_recon.py
demo/demo_4_wrong_rotation_direction.py
demo/demo_5_fbp_fdk.py
demo/demo_6_qggmrf_denoiser.py
demo/demo_slice_viewer.py
dev_scripts/QR-code/create-QR-code.py
docs/build/html/_static/new_model_template.py
docs/source/conf.py
docs/source/_static/new_model_template.py
experiments/start_viewer.py
experiments/alignment/alignment_experiment.py
experiments/alignment/alignment_utils.py
experiments/bugs_and_artifacts/jax rounding bug/jax_rounding_bug.py
experiments/bugs_and_artifacts/jax rounding bug/parallel_beam.py
experiments/bugs_and_artifacts/large_sharpness_slow_convergence/center_slice.py
experiments/coimg-2025/fourier_response.py
experiments/coimg-2025/spectral_convergence.py
experiments/coimg-2025/spectral_response.py
experiments/coimg-2025/subset_investigation.py
experiments/coimg-2025/vcd_coimg_utils.py
experiments/coimg-2025/vcd_figs_for_COIMG_2025.py
experiments/coimg-2025/vcd_psf.py
experiments/cvpr-2024/vcd_figs_for_abst_v1.py
experiments/cvpr-2024/vcd_figs_for_abst_v2.py
experiments/hsnt/example_1_denoise_simulated_data.py
experiments/hsnt/example_2_denoise_real_data.py
experiments/hsnt/example_3_test_hdf5_utils.py
experiments/hsnt/plot_utils.py
experiments/minimal_projectors/minimal_forward_projection.py
experiments/minimal_projectors/minimal_forward_projection_torch.py
experiments/par_cone/demo_1_shepp_logan.py
experiments/par_cone/demo_2_microscopy.py
experiments/prox_map/prox_map_experiment.py
experiments/prox_map/prox_test.py
experiments/sandboxes/cone_beam_dev.py
experiments/sandboxes/cube_phantom.py
experiments/sandboxes/hdf5_test.py
experiments/sandboxes/parallel_model_dev.py
experiments/sandboxes/projection_ray_display_test.py
experiments/sandboxes/qggmrf_denoiser_sandbox.py
experiments/sandboxes/recon_experiments.py
experiments/sandboxes/sandbox_shepp_logan.py
experiments/sandboxes/shepp_logan_convergence.py
experiments/sandboxes/slice_dependent_noise.py
mbirjax-0.6.12.dist-info/licenses/LICENSE
mbirjax-0.6.12.dist-info/METADATA
mbirjax-0.6.12.dist-info/WHEEL
mbirjax-0.6.12.dist-info/top_level.txt
mbirjax-0.6.12.dist-info/RECORD
