Metadata-Version: 2.4
Name: mbirjax
Version: 0.6.12
Summary: High-performance tomographic reconstruction
Author-email: MBIRJAX development team <buzzard@purdue.edu>
License: BSD 3-Clause License
Project-URL: homepage, https://mbirjax.readthedocs.io
Project-URL: source, https://github.com/cabouman/mbirjax
Keywords: tomography,tomographic reconstruction,computed tomography
Classifier: Programming Language :: Python :: 3
Classifier: Topic :: Scientific/Engineering :: Information Analysis
Classifier: License :: OSI Approved :: BSD License
Classifier: Operating System :: OS Independent
Requires-Python: >=3.9
License-File: LICENSE
Requires-Dist: jax
Requires-Dist: jaxlib
Requires-Dist: matplotlib
Requires-Dist: numpy
Requires-Dist: scipy
Requires-Dist: setuptools
Requires-Dist: ruamel.yaml
Requires-Dist: psutil
Requires-Dist: tifffile
Requires-Dist: h5py
Requires-Dist: dm-pix
Requires-Dist: tqdm
Requires-Dist: easygui
Requires-Dist: gdown
Requires-Dist: pywavelets
Requires-Dist: olefile
Requires-Dist: scikit-learn
Provides-Extra: cuda12
Requires-Dist: jax[cuda12]; extra == "cuda12"
Provides-Extra: test
Requires-Dist: pytest; extra == "test"
Provides-Extra: docs
Requires-Dist: sphinx; extra == "docs"
Requires-Dist: sphinxcontrib-bibtex; extra == "docs"
Requires-Dist: sphinx-book-theme>=1.0.1; extra == "docs"
Requires-Dist: sphinx-design; extra == "docs"
Requires-Dist: sphinx-copybutton; extra == "docs"
Dynamic: license-file
